pymifapi/__init__.py
pymifapi-0.1.1.dist-info/METADATA
pymifapi-0.1.1.dist-info/WHEEL
pymifapi-0.1.1.dist-info/entry_points.txt
pymifapi-0.1.1.dist-info/top_level.txt
pymifapi-0.1.1.dist-info/RECORD
